{
  "step_index": 19,
  "source": "MODEL",
  "type": "VIEW_FILE",
  "status": "DONE",
  "created_at": "2026-06-03T11:57:43Z",
  "content": "Created At: 2026-06-03T11:57:43Z\nCompleted At: 2026-06-03T11:57:43Z\nFile Path: `file:///Applications/sahil_MP_app/APP/mantrapuja/scratch/get_schema.js`\nTotal Lines: 50\nTotal Bytes: 1509\nShowing lines 1 to 50\nThe following code has been modified to include a line number before every line, in the format: <line_number>: <original_line>. Please note that any changes targeting the original code should remove the line number, colon, and leading space.\n1: const { createClient } = require('@supabase/supabase-js');\n2: \n3: const supabaseUrl = 'https://vjkwmefdutltwccpgnny.supabase.co';\n4: const supabaseAnonKey = 'sb_publishable_gZzOlAfCHCDDgdTbMop8zQ_18bQRX0L';\n5: \n6: const supabase = createClient(supabaseUrl, supabaseAnonKey);\n7: \n8: async function check() {\n9:   try {\n10:     console.log('Querying website_pooja_products...');\n11:     const { data: prodData, error: prodErr } = await supabase\n12:       .from('website_pooja_products')\n13:       .select('*')\n14:       .limit(1);\n15: \n16:     if (prodErr) {\n17:       console.error('Error fetching website_pooja_products:', prodErr);\n18:     } else {\n19:       console.log('website_pooja_products sample row:');\n20:       if (prodData && prodData[0]) {\n21:         for (const [key, val] of Object.entries(prodData[0])) {\n22:           console.log(`- ${key}: ${val === null ? 'NULL' : typeof val} (sample: ${JSON.stringify(val)})`);\n23:         }\n24:       } else {\n25:         console.log('No rows found in website_pooja_products');\n26:       }\n27:     }\n28: \n29:     console.log('\\nQuerying website_settings...');\n30:     const { data: setRecs, error: setErr } = await supabase\n31:       .from('website_settings')\n32:       .select('*');\n33: \n34:     if (setErr) {\n35:       console.error('Error fetching website_settings:', setErr);\n36:     } else {\n37:       console.log('website_settings rows:');\n38:       if (setRecs) {\n39:         setRecs.forEach(r => {\n40:           console.log(`- key: ${r.key}, value type: ${typeof r.value}, sample: ${JSON.stringify(r.value)}`);\n41:         });\n42:       }\n43:     }\n44:   } catch (err) {\n45:     console.error(err);\n46:   }\n47: }\n48: \n49: check();\n50: \nThe above content shows the entire, complete file contents of the requested file.\n"
}