{
  "step_index": 732,
  "source": "MODEL",
  "type": "VIEW_FILE",
  "status": "DONE",
  "created_at": "2026-05-29T10:53:04Z",
  "content": "Created At: 2026-05-29T10:53:04Z\nCompleted At: 2026-05-29T10:53:04Z\nFile Path: `file:///Users/sahilpatel/Desktop/New_Mantra_puja/Store/src/components/AdminPanelPage.tsx`\nTotal Lines: 2684\nTotal Bytes: 132774\nShowing lines 130 to 180\nThe following code has been modified to include a line number before every line, in the format: <line_number>: <original_line>. Please note that any changes targeting the original code should remove the line number, colon, and leading space.\n130:   const [selectedPoojaIds, setSelectedPoojaIds] = React.useState<Record<string, boolean>>({});\n131:   const [isBulkPublishing, setIsBulkPublishing] = React.useState(false);\n132: \n133:   const handleBulkPublishPooja = async () => {\n134:     const idsToPublish = Object.keys(selectedPoojaIds).filter(id => selectedPoojaIds[id]);\n135:     if (idsToPublish.length === 0) {\n136:       alert('Please select at least one Pooja product draft to publish.');\n137:       return;\n138:     }\n139: \n140:     if (window.confirm(`Are you sure you want to publish the ${idsToPublish.length} selected Pooja product drafts to the live website?`)) {\n141:       setIsBulkPublishing(true);\n142:       try {\n143:         const { error } = await supabase\n144:           .from('website_pooja_products')\n145:           .update({ is_published: true, published_at: new Date().toISOString() })\n146:           .in('id', idsToPublish);\n147: \n148:         if (error) throw error;\n149: \n150:         triggerToast(`Successfully published ${idsToPublish.length} Pooja products to live website!`);\n151:         setSelectedPoojaIds({});\n152:         loadPoojaProducts();\n153:       } catch (err) {\n154:         console.error(err);\n155:         alert('Failed to publish: ' + (err as Error).message);\n156:       } finally {\n157:         setIsBulkPublishing(false);\n158:       }\n159:     }\n160:   };\n161: \n162:   const poojaTemplates: Array<Partial<PoojaProduct> & { id: string }> = [\n163:     {\n164:       id: 'template-mrityunjaya',\n165:       name: 'Maha Mrityunjaya Havan',\n166:       sanskritName: 'महामृत्युंजय हवन यज्ञ',\n167:       shortName: 'Mrityunjaya Havan',\n168:       slug: 'maha-mrityunjaya-havan',\n169:       category: 'Siddh Range',\n170:       subtitle: 'Divine protective chanting & sacred fire offerings',\n171:       shortDescription: 'Sacred Vedic fire ritual for profound healing, longevity, and health alignment.',\n172:       description: 'The Maha Mrityunjaya ritual is one of the most powerful Vedic ceremonies. Performed by elite Banaras Acharyas, it invokes Lord Shiva\\'s rejuvenating energy to dissolve chronic obstacles, restore physical vitality, and secure a protective shield for the performer\\'s entire family.',\n173:       spiritualSignificance: 'According to ancient Upanishadic scriptures, the Maha Mrityunjaya mantra represents the conquering of cosmic fears and physical decay, restoring energetic flow to the performer.',\n174:       bookingInstructions: '1. Enter the full name, Gotra, and Nakshatra of the performer.\\n2. Sit facing East during the live stream session.\\n3. Keep a copper plate and fresh flowers near you for Sankalpa.',\n175:       duration: '3 Hours',\n176:       templeAssociation: 'Mahamrityunjay Temple, Varanasi',\n177:       whoShouldPerform: 'Individuals seeking health rejuvenation, chronic obstacle removal, and longevity.',\n178:       ritualsIncluded: [\n179:         { name: 'Ganesh Ambika Pujan', description: 'Initial invocation for obstacle removal.', duration: '20 mins' },\n180:         { name: 'Shiva Linga Abhishek', description: 'Aromatic milk and honey offering to the Shiva Linga.', duration: '40 mins' },\nThe above content does NOT show the entire file contents. If you need to view any lines of the file which were not shown to complete your task, call this tool again to view those lines.\n"
}